concepts/__init__.py
concepts/_compat.py
concepts/_compat_csv.py
concepts/contexts.py
concepts/definitions.py
concepts/formats.py
concepts/junctors.py
concepts/lattices.py
concepts/matrices.py
concepts/tools.py
concepts/visualize.py
concepts-0.9.2.dist-info/LICENSE.txt
concepts-0.9.2.dist-info/METADATA
concepts-0.9.2.dist-info/WHEEL
concepts-0.9.2.dist-info/top_level.txt
concepts-0.9.2.dist-info/RECORD
