Metadata-Version: 2.1
Name: concepts
Version: 0.9.2
Summary: Formal Concept Analysis with Python
Home-page: https://github.com/xflr6/concepts
Author: Sebastian Bank
Author-email: sebastian.bank@uni-leipzig.de
License: MIT
Project-URL: Documentation, https://concepts.readthedocs.io
Project-URL: Changelog, https://concepts.readthedocs.io/en/latest/changelog.html
Project-URL: Issue Tracker, https://github.com/xflr6/concepts/issues
Keywords: fca complete lattice graph join meet galois
Platform: any
Classifier: Development Status :: 4 - Beta
Classifier: Intended Audience :: Developers
Classifier: Intended Audience :: Science/Research
Classifier: License :: OSI Approved :: MIT License
Classifier: Operating System :: OS Independent
Classifier: Programming Language :: Python :: 2
Classifier: Programming Language :: Python :: 2.7
Classifier: Programming Language :: Python :: 3
Classifier: Programming Language :: Python :: 3.5
Classifier: Programming Language :: Python :: 3.6
Classifier: Programming Language :: Python :: 3.7
Classifier: Programming Language :: Python :: 3.8
Classifier: Topic :: Scientific/Engineering :: Information Analysis
Classifier: Topic :: Scientific/Engineering :: Mathematics
Classifier: Topic :: Scientific/Engineering :: Visualization
Requires-Python: >=2.7,!=3.0.*,!=3.1.*,!=3.2.*,!=3.3.*,!=3.4.*
Provides-Extra: dev
Provides-Extra: test
Provides-Extra: docs
